odoo/addons/test_base_geoengine/README.rst
odoo/addons/test_base_geoengine/__init__.py
odoo/addons/test_base_geoengine/__manifest__.py
odoo/addons/test_base_geoengine/models.py
odoo/addons/test_base_geoengine/views.xml
odoo/addons/test_base_geoengine/i18n/test_base_geoengine.pot
odoo/addons/test_base_geoengine/security/ir.model.access.csv
odoo/addons/test_base_geoengine/static/description/icon.png
odoo/addons/test_base_geoengine/tests/__init__.py
odoo/addons/test_base_geoengine/tests/data.py
odoo/addons/test_base_geoengine/tests/test_base_geoengine.py
odoo13_addon_test_base_geoengine-13.0.1.0.1.dev9.dist-info/METADATA
odoo13_addon_test_base_geoengine-13.0.1.0.1.dev9.dist-info/WHEEL
odoo13_addon_test_base_geoengine-13.0.1.0.1.dev9.dist-info/top_level.txt
odoo13_addon_test_base_geoengine-13.0.1.0.1.dev9.dist-info/RECORD
